eightdad/__init__.py
eightdad/tst.py
eightdad/core/__init__.py
eightdad/core/bytecode.py
eightdad/core/video.py
eightdad/core/vm.py
eightdad/tools/__init__.py
eightdad-0.0.1.dist-info/LICENSE
eightdad-0.0.1.dist-info/METADATA
eightdad-0.0.1.dist-info/WHEEL
eightdad-0.0.1.dist-info/top_level.txt
eightdad-0.0.1.dist-info/RECORD
