Metadata-Version: 2.1
Name: eightdad
Version: 0.0.1
Summary: Chip-8 interpreter that might one day also have other tools
Home-page: https://github.com/pushfoo/eightdad
Author: pushfoo
Author-email: pushfoo@gmail.com
License: BSD-2-Clause
Platform: UNKNOWN
Classifier: Development Status :: 2 - Pre-Alpha
Classifier: Programming Language :: Python :: 3
Classifier: License :: OSI Approved :: BSD License
Classifier: Operating System :: OS Independent
Classifier: Topic :: Software Development :: Interpreters
Classifier: Topic :: System :: Emulators
Requires-Python: >=3.6
Requires-Dist: bitarray
